[
  {
    "id": "cng-117c1c98",
    "name": "Bharat Petroleum",
    "latitude": 31.60096,
    "longitude": 76.17792,
    "city": "",
    "state": "Punjab",
    "source": "osm",
    "address": "Punjab"
  },
  {
    "id": "cng-77781121",
    "name": "Bharat Petroleum",
    "latitude": 31.389969,
    "longitude": 76.344562,
    "city": "",
    "state": "Punjab",
    "source": "osm",
    "address": "Punjab"
  },
  {
    "id": "cng-3c9612a9",
    "name": "Chaudhary Fuel Point",
    "latitude": 31.350737,
    "longitude": 76.387524,
    "city": "",
    "state": "Punjab",
    "source": "osm",
    "address": "Punjab"
  },
  {
    "id": "cng-77577dfd",
    "name": "Cng Station",
    "latitude": 30.89107,
    "longitude": 75.80206,
    "city": "",
    "state": "Punjab",
    "source": "osm",
    "address": "Punjab"
  },
  {
    "id": "cng-1779d1fd",
    "name": "Sarpanch Petro Service",
    "latitude": 30.50516,
    "longitude": 74.858002,
    "city": "",
    "state": "Punjab",
    "source": "osm",
    "address": "Jaito- Bathinda Road, Punjab"
  },
  {
    "id": "cng-26101335",
    "name": "Grand Filling Petrol & Cng Station",
    "latitude": 30.289477,
    "longitude": 76.348328,
    "city": "Sher Majra",
    "state": "Punjab",
    "source": "osm",
    "address": "Sher Majra, Punjab"
  }
]
